compareVersions.py
compare_versions_s528358-0.0.1.post2.dist-info/LICENSE
compare_versions_s528358-0.0.1.post2.dist-info/METADATA
compare_versions_s528358-0.0.1.post2.dist-info/WHEEL
compare_versions_s528358-0.0.1.post2.dist-info/top_level.txt
compare_versions_s528358-0.0.1.post2.dist-info/RECORD
