Metadata-Version: 2.1
Name: compare-versions-s528358
Version: 0.0.1.post2
Summary: script to compare versions
Home-page: https://github.com/ashishiit/Ashish_Jamuda_test/tree/master/Problem%20B
Author: Ashish Jamuda
Author-email: ashish.turbobit@gmail.com
License: UNKNOWN
Platform: UNKNOWN
Classifier: Programming Language :: Python :: 3
Classifier: Programming Language :: Python :: 3.6
Classifier: Programming Language :: Python :: 3.7
Classifier: License :: OSI Approved :: MIT License
Classifier: Operating System :: OS Independent
Requires-Python: >=3.6
